stravabackup/__init__.py
stravabackup/__main__.py
stravabackup/strava-backup.conf
strava_backup-0.4.0.dist-info/METADATA
strava_backup-0.4.0.dist-info/WHEEL
strava_backup-0.4.0.dist-info/entry_points.txt
strava_backup-0.4.0.dist-info/top_level.txt
strava_backup-0.4.0.dist-info/RECORD
