Metadata-Version: 2.4
Name: strava-backup
Version: 0.4.0
Summary: Get your data back from Strava
Home-page: https://github.com/pR0Ps/strava-backup
License: MPLv2
Classifier: Programming Language :: Python :: 3
Classifier: Programming Language :: Python :: 3 :: Only
Requires-Python: >=3.8
Requires-Dist: stravaweblib<1.0.0,>=0.0.9
Requires-Dist: stravalib<1.0.0,>=0.10.4
Requires-Dist: commented-configparser<3,>=2
Dynamic: classifier
Dynamic: description
Dynamic: description-content-type
Dynamic: home-page
Dynamic: license
Dynamic: requires-dist
Dynamic: requires-python
Dynamic: summary
